Workbook

Sheet CUSTO
A1: CONTAGEM CAFÉ DA MANHÃ
A2: ITEM | B2: PESO INICIAL | C2: REPOSIÇÃO | D2: DESPERDICIO | E2: VOLTA | F2: CONSUMO | G2: PREÇO KG | H2: VALOR REAL
A3: ABACAXI | B3: 0.868 | E3: 0.448 | F3: =B3+C3-E3 -> 0.42 | G3: 4.05 | H3: =F3*G3 -> 1.701
A4: AÇUCAR | F4: =B4+C4-E4 -> 0 | H4: =F4*G4 -> 0
A5: AÇUCAR MASKAVO | F5: =B5+C5-E5 -> 0 | H5: =F5*G5 -> 0
A6: AÇUCAR ORGANICO | F6: =B6+C6-E6 -> 0 | H6: =F6*G6 -> 0
A7: ADOCANTE | F7: =B7+C7-E7 -> 0 | H7: =F7*G7 -> 0
A8: AGUA | F8: =B8+C8-E8 -> 0 | H8: =F8*G8 -> 0
A9: AGUA COM GAS | B9: 1 | E9: 1 | F9: =B9+C9-E9 -> 0 | G9: 9.05 | H9: =F9*G9 -> 0
A10: AGUA SABORIZADA | F10: =B10+C10-E10 -> 0 | H10: =F10*G10 -> 0
A11: AMEIXA | B11: 0.594 | E11: 0.544 | F11: =B11+C11-E11 -> 0.05 | G11: 33.93 | H11: =F11*G11 -> 1.6965
A12: AVEIA | B12: 0.624 | E12: 0.518 | F12: =B12+C12-E12 -> 0.106 | G12: =11.97*2 -> 23.94 | H12: =F12*G12 -> 2.53764
A13: BAGUETE | F13: =B13+C13-E13 -> 0 | H13: =F13*G13 -> 0
A14: BAGUETE MULTI | F14: =B14+C14-E14 -> 0 | H14: =F14*G14 -> 0
A15: BAGUETE PARMESAO | F15: =B15+C15-E15 -> 0 | H15: =F15*G15 -> 0
A16: BATATA BOLINHA | F16: =B16+C16-E16 -> 0 | H16: =F16*G16 -> 0
A17: BATATA DOCE | B17: 1.318 | E17: 0.646 | F17: =B17+C17-E17 -> 0.672 | G17: 5.36 | H17: =F17*G17 -> 3.60192
A18: BOLO | B18: 1.64 | E18: 0.386 | F18: =B18+C18-E18 -> 1.254 | G18: 7.01 | H18: =F18*G18 -> 8.79054
A19: BOLO COM COBERTURA | F19: =B19+C19-E19 -> 0 | H19: =F19*G19 -> 0
A20: BOLO SEM GLUTEN | F20: =B20+C20-E20 -> 0 | H20: =F20*G20 -> 0
A21: CAFÉ COADO | B21: 0.75 | E21: 0 | F21: =B21+C21-E21 -> 0.75 | G21: 94.3 | H21: =F21*G21 -> 70.725
A22: CAFÉ MAQUINA | B22: 1.65 | E22: 1.364 | F22: =B22+C22-E22 -> 0.286 | G22: 94.3 | H22: =F22*G22 -> 26.9698
A23: CAJU | F23: =B23+C23-E23 -> 0 | H23: =F23*G23 -> 0
A24: CALABRESA | B24: 1.272 | E24: 0.672 | F24: =B24+C24-E24 -> 0.6 | G24: 18.99 | H24: =F24*G24 -> 11.394
A25: CANELA | F25: =B25+C25-E25 -> 0 | H25: =F25*G25 -> 0
A26: CAPUCCINO MAQUINA | B26: 1.28 | E26: 0.876 | F26: =B26+C26-E26 -> 0.404 | G26: 88.62 | H26: =F26*G26 -> 35.80248
A27: CAROLINA DOCE DE LEITE | F27: =B27+C27-E27 -> 0 | H27: =F27*G27 -> 0
A28: CHA DE CAPIM CIDREIRA | B28: 9 | E28: 8 | F28: =B28+C28-E28 -> 1 | G28: 0.42 | H28: =F28*G28 -> 0.42
A29: CHA DE HORTELA | F29: =B29+C29-E29 -> 0 | H29: =F29*G29 -> 0
A30: CHA DE CAMOMILA | B30: 12 | E30: 11 | F30: =B30+C30-E30 -> 1 | G30: =6.46/15 -> 0.43066667 | H30: =F30*G30 -> 0.43066667
A31: CHA DE MORANGO | B31: 6 | E31: 5 | F31: =B31+C31-E31 -> 1 | G31: 0.59 | H31: =F31*G31 -> 0.59
A32: CHA GELADO | F32: =B32+C32-E32 -> 0 | H32: =F32*G32 -> 0
A33: CHA MATE | B33: 10 | E33: 10 | F33: =B33+C33-E33 -> 0 | G33: =6.46/15 -> 0.43066667 | H33: =F33*G33 -> 0
A34: CHIA | B34: 0.156 | E34: 0.114 | F34: =B34+C34-E34 -> 0.042 | G34: 22 | H34: =F34*G34 -> 0.924
A35: CHOCOLATE | B35: 0.968 | E35: 0.522 | F35: =B35+C35-E35 -> 0.446 | G35: 77.14 | H35: =F35*G35 -> 34.40444
A36: CHOCOLATE CEREAL | B36: 0.162 | E36: 0.1 | F36: =B36+C36-E36 -> 0.062 | G36: 40.4 | H36: =F36*G36 -> 2.5048
A37: CHURROS | B37: 1 | E37: 0.074 | F37: =B37+C37-E37 -> 0.926 | G37: 28.11 | H37: =F37*G37 -> 26.02986
A38: CHOCOLATE EM PO | F38: =B38+C38-E38 -> 0 | H38: =F38*G38 -> 0
A39: COMPOTA DE FIGO | F39: =B39+C39-E39 -> 0 | H39: =F39*G39 -> 0
A40: COMPOTA DE MARACUJA | F40: =B40+C40-E40 -> 0 | H40: =F40*G40 -> 0
A41: CREAM CHESSE | B41: 66 | E41: 42 | F41: =B41+C41-E41 -> 24 | G41: 1.02 | H41: =F41*G41 -> 24.48
A42: CROASSAINT | F42: =B42+C42-E42 -> 0 | H42: =F42*G42 -> 0
A43: CROASSAINT CATUPIRY | F43: =B43+C43-E43 -> 0 | H43: =F43*G43 -> 0
A44: SUCO DETOX | B44: 2 | C44: 1.5 | E44: 0.5 | F44: =B44+C44-E44 -> 3 | G44: =4.05+3.66+1.9+0.28+8.84*3 -> 36.41 | H44: =F44*G44 -> 109.23
A45: DONUTS | F45: =B45+C45-E45 -> 0 | H45: =F45*G45 -> 0
A46: ENROLADO SALCICHA | F46: =B46+C46-E46 -> 0 | H46: =F46*G46 -> 0
A47: ESFIHA | F47: =B47+C47-E47 -> 0 | H47: =F47*G47 -> 0
A48: FOLHADO CALABRESA | F48: =B48+C48-E48 -> 0 | H48: =F48*G48 -> 0
A49: GANACHE | F49: =B49+C49-E49 -> 0 | H49: =F49*G49 -> 0
A50: GELEIA GOIABA | B50: 50 | E50: 42 | F50: =B50+C50-E50 -> 8 | G50: 0.29 | H50: =F50*G50 -> 2.32
A51: GELIA MORANGO | F51: =B51+C51-E51 -> 0 | H51: =F51*G51 -> 0
A52: GRANOLA | F52: =B52+C52-E52 -> 0 | H52: =F52*G52 -> 0
A53: IOGURTE DESNATADO | B53: 10 | E53: 7 | F53: =B53+C53-E53 -> 3 | G53: 3.39 | H53: =F53*G53 -> 10.17
A54: IOGURTE NATURAL | B54: 10 | E54: 6 | F54: =B54+C54-E54 -> 4 | G54: 3.39 | H54: =F54*G54 -> 13.56
A55: IOGURTE DE MORANGO | B55: 1 | E55: 0.08 | F55: =B55+C55-E55 -> 0.92 | G55: 15.6 | H55: =F55*G55 -> 14.352
A56: LEITE DESNATADO | B56: 1 | F56: =B56+C56-E56 -> 1 | G56: 5.35 | H56: =F56*G56 -> 5.35
A57: LEITE INTEGRAL | B57: 7 | E57: =0.87+1.04+3 -> 4.91 | F57: =B57+C57-E57 -> 2.09 | G57: 5.35 | H57: =F57*G57 -> 11.1815
A58: LEITE SEM LACTOSE | F58: =B58+C58-E58 -> 0 | H58: =F58*G58 -> 0
A59: LEITE SOJA | F59: =B59+C59-E59 -> 0 | H59: =F59*G59 -> 0
A60: LINHAÇA | B60: 0.426 | E60: =0.58-0.172 -> 0.408 | F60: =B60+C60-E60 -> 0.018 | G60: 9.99 | H60: =F60*G60 -> 0.17982
A61: MAÇA VERDE | F61: =B61+C61-E61 -> 0 | H61: =F61*G61 -> 0
A62: MAÇA VERMELHA | F62: =B62+C62-E62 -> 0 | H62: =F62*G62 -> 0
A63: MAMAO | B63: 0.68 | C63: 1.1018 | E63: 0.102 | F63: =B63+C63-E63 -> 1.6798 | G63: 4.33 | H63: =F63*G63 -> 7.273534
A64: MANTEIGA COM SAL | B64: 45 | E64: 39 | F64: =B64+C64-E64 -> 6 | G64: 0.84 | H64: =F64*G64 -> 5.04
A65: MANTEIGA SEM SAL | B65: 63 | E65: 32 | F65: =B65+C65-E65 -> 31 | G65: 0.84 | H65: =F65*G65 -> 26.04
A66: MEL SACHET | B66: 30 | E66: 22 | F66: =B66+C66-E66 -> 8 | G66: 0.52 | H66: =F66*G66 -> 4.16
A67: MELANCIA | B67: 1.664 | C67: 1.952 | E67: 1.822 | F67: =B67+C67-E67 -> 1.794 | G67: 3.19 | H67: =F67*G67 -> 5.72286
A68: MELÃO | B68: 1.39 | C68: 0.948 | E68: 0.972 | F68: =B68+C68-E68 -> 1.366 | G68: 10.6 | H68: =F68*G68 -> 14.4796
A69: MEXERICA | F69: =B69+C69-E69 -> 0 | H69: =F69*G69 -> 0
A70: MILHO | B70: =2.302-0.746 -> 1.556 | E70: =1.276-0.746 -> 0.53 | F70: =B70+C70-E70 -> 1.026 | G70: 8.12 | H70: =F70*G70 -> 8.33112
A71: MINI FRANCES | F71: =B71+C71-E71 -> 0 | H71: =F71*G71 -> 0
A72: MINI PÃO CENOURA | F72: =B72+C72-E72 -> 0 | H72: =F72*G72 -> 0
A73: MINI CAROLINA DE MARACUJA | B73: 10 | E73: 7 | F73: =B73+C73-E73 -> 3 | G73: =13.2/10 -> 1.32 | H73: =F73*G73 -> 3.96
A74: MINI ROSETA DE PARMESÃO | B74: 5 | E74: 2 | F74: =B74+C74-E74 -> 3 | G74: =6.25/5 -> 1.25 | H74: =F74*G74 -> 3.75
A75: MINI BISNAGA C/ CREME 30G | B75: 10 | E75: 8 | F75: =B75+C75-E75 -> 2 | G75: =9.6/10 -> 0.96 | H75: =F75*G75 -> 1.92
A76: MINI CIABATA SIMPLES | B76: 10 | E76: 10 | F76: =B76+C76-E76 -> 0 | G76: =9.9/10 -> 0.99 | H76: =F76*G76 -> 0
A77: MINI QUICHES DE ALHO PORRO | B77: 20 | E77: 10 | F77: =B77+C77-E77 -> 10 | G77: =48.4/20 -> 2.42 | H77: =F77*G77 -> 24.2
A78: MINI BISNAGA C/ COCO 30G | B78: 10 | E78: 10 | F78: =B78+C78-E78 -> 0 | G78: =9.6/10 -> 0.96 | H78: =F78*G78 -> 0
A79: BAGUETE SIMPLES 60CM | B79: 1 | E79: 0.5 | F79: =B79+C79-E79 -> 0.5 | G79: 11.66 | H79: =F79*G79 -> 5.83
A80: MINI SONHO CREME | B80: 10 | E80: 6 | F80: =B80+C80-E80 -> 4 | G80: =13.2/10 -> 1.32 | H80: =F80*G80 -> 5.28
A81: MINI CROISSANT DE PRESUNTO E QUEIJO | B81: 20 | E81: 14 | F81: =B81+C81-E81 -> 6 | G81: =27.6/20 -> 1.38 | H81: =F81*G81 -> 8.28
A82: MINI BOLINHO DE CHUVA | B82: 20 | E82: 14 | F82: =B82+C82-E82 -> 6 | G82: =16/20 -> 0.8 | H82: =F82*G82 -> 4.8
A83: MINI CROISSANT DE CREME | B83: 10 | E83: 7 | F83: =B83+C83-E83 -> 3 | G83: =13.8/10 -> 1.38 | H83: =F83*G83 -> 4.14
A84: MINI SONHO DE DOCE DE LEITE | B84: 10 | E84: 8 | F84: =B84+C84-E84 -> 2 | G84: =13.2/10 -> 1.32 | H84: =F84*G84 -> 2.64
A85: BAGUETE PARMESÃO - 60CM | B85: 1 | E85: 1 | F85: =B85+C85-E85 -> 0 | G85: 14.41 | H85: =F85*G85 -> 0
A86: MINI PÃO DE BATATA SIMPLES 30G | B86: 10 | E86: 4 | F86: =B86+C86-E86 -> 6 | G86: =9.9/10 -> 0.99 | H86: =F86*G86 -> 5.94
A87: MINI CROISANT DE CALABRESA | B87: 10 | E87: 9 | F87: =B87+C87-E87 -> 1 | G87: =13.8/10 -> 1.38 | H87: =F87*G87 -> 1.38
A88: MINI PÃO FRANCÊS 30G | B88: 50 | E88: 27 | F88: =B88+C88-E88 -> 23 | G88: =34/50 -> 0.68 | H88: =F88*G88 -> 15.64
A89: MINI CROISSANT DE CHOCOLATE | B89: 10 | E89: 2 | F89: =B89+C89-E89 -> 8 | G89: =13.81 -> 13.81 | H89: =F89*G89 -> 110.48
A90: MINI ROSETA DE AÇÚCAR | B90: 5 | E90: 5 | F90: =B90+C90-E90 -> 0 | G90: =5.05/5 -> 1.01 | H90: =F90*G90 -> 0
A91: MINI ROSETA DE LARANJA | B91: 5 | E91: 5 | F91: =B91+C91-E91 -> 0 | G91: =4.8/5 -> 0.96 | H91: =F91*G91 -> 0
A92: MINI PÃO FRANCÊS INTEGRAL 30G | B92: 10 | E92: 10 | F92: =B92+C92-E92 -> 0 | G92: =8.5/10 -> 0.85 | H92: =F92*G92 -> 0
A93: MINI PÃO DE BATATA C/ CALABRESA 30G | B93: 10 | E93: 8 | F93: =B93+C93-E93 -> 2 | G93: =12.4/10 -> 1.24 | H93: =F93*G93 -> 2.48
A94: MINI ROSETA DE COCO | B94: 5 | E94: 2 | F94: =B94+C94-E94 -> 3 | G94: =5.05/5 -> 1.01 | H94: =F94*G94 -> 3.03
A95: MINI BOMBA DE CREME | B95: 10 | E95: 8 | F95: =B95+C95-E95 -> 2 | G95: =13.2/10 -> 1.32 | H95: =F95*G95 -> 2.64
A96: MINI PÃO MULTIGRÃO RESONDO 30G | B96: 5 | E96: 4 | F96: =B96+C96-E96 -> 1 | G96: =6.05/5 -> 1.21 | H96: =F96*G96 -> 1.21
A97: MINI CARACOL C/ MAÇÃ | B97: 10 | E97: 7 | F97: =B97+C97-E97 -> 3 | G97: =13/10 -> 1.3 | H97: =F97*G97 -> 3.9
A98: MINI BOMBA DE CHOCOLATE | B98: 10 | E98: 10 | F98: =B98+C98-E98 -> 0 | G98: =13.2/10 -> 1.32 | H98: =F98*G98 -> 0
A99: MINI BOMBA DE DOCE DE LEITE | B99: 10 | E99: 0 | F99: =B99+C99-E99 -> 10 | G99: =13.2/10 -> 1.32 | H99: =F99*G99 -> 13.2
A100: MINI BRIOCHE SIMPLES | B100: 5 | E100: 5 | F100: =B100+C100-E100 -> 0 | G100: =5.4/5 -> 1.08 | H100: =F100*G100 -> 0
...

Sheet DESPERDICIO
A1: ITEM | B1: PESO INICIAL | C1: REPOSIÇÃO | D1: DESPERDICIO | E1: VOLTA | F1: CONSUMO | G1: PREÇO KG | H1: VALOR REAL
A2: ABACAXI | B2: 0.868 | E2: 0.448 | F2: =B2+C2-E2 -> 0.42 | G2: 4.05 | H2: =F2*G2 -> 1.701 | I2: LIXO
A3: BATATA DOCE | B3: 1.318 | E3: 0.646 | F3: =B3+C3-E3 -> 0.672 | G3: 5.36 | H3: =F3*G3 -> 3.60192 | I3: LIXO
A4: BOLO | B4: 1.64 | E4: 0.386 | F4: =B4+C4-E4 -> 1.254 | G4: 7.01 | H4: =F4*G4 -> 8.79054 | I4: LIXO
A5: CALABRESA | B5: 1.272 | E5: 0.672 | F5: =B5+C5-E5 -> 0.6 | G5: 18.99 | H5: =F5*G5 -> 11.394 | I5: LIXO
A6: CHOCOLATE | B6: 0.968 | E6: 0.522 | F6: =B6+C6-E6 -> 0.446 | G6: 107.52 | H6: =F6*G6 -> 47.95392 | I6: LIXO
A7: SUCO DETOX | B7: 2 | C7: 1.5 | E7: 0.5 | F7: =B7+C7-E7 -> 3 | G7: =4.05+3.66+1.9+0.28+8.84*3 -> 36.41 | H7: =F7*G7 -> 109.23 | I7: LIXO
A8: IOGURTE DE MORANGO | B8: 1 | E8: 0.08 | F8: =B8+C8-E8 -> 0.92 | G8: 15.6 | H8: =F8*G8 -> 14.352 | I8: LIXO
A9: LEITE INTEGRAL | B9: 7 | E9: =0.87+1.04+3 -> 4.91 | F9: =B9+C9-E9 -> 2.09 | G9: 5.35 | H9: =F9*G9 -> 11.1815 | I9: LIXO
A10: MAMAO | B10: 0.68 | C10: 1.1018 | E10: 0.102 | F10: =B10+C10-E10 -> 1.6798 | G10: 4.33 | H10: =F10*G10 -> 7.273534 | I10: LIXO
A11: MELANCIA | B11: 1.664 | C11: 1.952 | E11: 1.822 | F11: =B11+C11-E11 -> 1.794 | G11: 3.19 | H11: =F11*G11 -> 5.72286 | I11: LIXO
A12: MELÃO | B12: 1.39 | C12: 0.948 | E12: 0.972 | F12: =B12+C12-E12 -> 1.366 | G12: 10.6 | H12: =F12*G12 -> 14.4796 | I12: LIXO
A13: MILHO | B13: =2.302-0.746 -> 1.556 | E13: =1.276-0.746 -> 0.53 | F13: =B13+C13-E13 -> 1.026 | G13: 8.12 | H13: =F13*G13 -> 8.33112 | I13: LIXO
A14: MINI BISNAGA C/ CREME 30G | B14: 10 | E14: 8 | F14: =B14+C14-E14 -> 2 | G14: =9.6/10 -> 0.96 | H14: =F14*G14 -> 1.92 | I14: LIXO
A15: BAGUETE SIMPLES 60CM | B15: 1 | E15: 0.5 | F15: =B15+C15-E15 -> 0.5 | G15: 11.66 | H15: =F15*G15 -> 5.83 | I15: LIXO
A16: MINI PÃO DE BATATA SIMPLES 30G | B16: 10 | E16: 4 | F16: =B16+C16-E16 -> 6 | G16: =9.9/10 -> 0.99 | H16: =F16*G16 -> 5.94 | I16: LIXO
A17: MINI PÃO FRANCÊS 30G | B17: 50 | E17: 27 | F17: =B17+C17-E17 -> 23 | G17: =34/50 -> 0.68 | H17: =F17*G17 -> 15.64 | I17: LIXO
A18: MINI ROSETA DE COCO | B18: 5 | E18: 2 | F18: =B18+C18-E18 -> 3 | G18: =5.05/5 -> 1.01 | H18: =F18*G18 -> 3.03 | I18: LIXO
A19: MINI PÃO MULTIGRÃO RESONDO 30G | B19: 5 | E19: 4 | F19: =B19+C19-E19 -> 1 | G19: =6.05/5 -> 1.21 | H19: =F19*G19 -> 1.21 | I19: LIXO
A20: MINI PÃO DE BETERRABA 30G | B20: 5 | E20: 4 | F20: =B20+C20-E20 -> 1 | G20: =6.05/5 -> 1.21 | H20: =F20*G20 -> 1.21 | I20: LIXO
A21: MINI PÃO DE MILHO REDONDO | B21: 5 | E21: 3 | F21: =B21+C21-E21 -> 2 | G21: =4.95/5 -> 0.99 | H21: =F21*G21 -> 1.98 | I21: LIXO
A22: MUSSARELA | B22: 0.7 | E22: 0.252 | F22: =B22+C22-E22 -> 0.448 | G22: 41.9 | H22: =F22*G22 -> 18.7712 | I22: LIXO
A23: MIX DE SALADAS | B23: 0.25 | E23: 0.23 | F23: =B23+C23-E23 -> 0.02 | G23: 56.07 | H23: =F23*G23 -> 1.1214 | I23: LIXO
A24: OVO MEXIDO | B24: 5 | E24: 1.616 | F24: =B24+C24-E24 -> 3.384 | G24: 16.9 | H24: =F24*G24 -> 57.1896 | I24: LIXO
A25: OVO COZIDO | B25: 14 | E25: 10 | F25: =B25+C25-E25 -> 4 | G25: 0.5 | H25: =F25*G25 -> 2 | I25: LIXO
A26: PÃO DE QUEIJO | B26: =2.032 -> 2.032 | C26: =2.062+0.722 -> 2.784 | E26: 1.914 | F26: =B26+C26-E26 -> 2.902 | G26: 16.25 | H26: =F26*G26 -> 47.1575 | I26: LIXO
A27: PEITO DE PERU | B27: 0.494 | E27: 0.27 | F27: =B27+C27-E27 -> 0.224 | G27: 44.41 | H27: =F27*G27 -> 9.94784 | I27: LIXO
A28: PRESUNTO | B28: 0.706 | E28: 0.342 | F28: =B28+C28-E28 -> 0.364 | G28: 28.9 | H28: =F28*G28 -> 10.5196 | I28: LIXO
A29: QUEIJO MINAS | B29: 0.976 | E29: 0.213 | F29: =B29+C29-E29 -> 0.763 | G29: 36.65 | H29: =F29*G29 -> 27.96395 | I29: LIXO
A30: QUEIJO PRATO | B30: 0.7 | E30: 0.23 | F30: =B30+C30-E30 -> 0.47 | G30: 41.78 | H30: =F30*G30 -> 19.6366 | I30: LIXO
A31: QUICHE | B31: =1.67-0.804 -> 0.866 | E31: =1.152-0.804 -> 0.348 | F31: =B31+C31-E31 -> 0.518 | G31: 11.85 | H31: =F31*G31 -> 6.1383 | I31: LIXO
A32: SALSICHA | B32: =3.624-0.998 -> 2.626 | E32: =2.474-0.998 -> 1.476 | F32: =B32+C32-E32 -> 1.15 | G32: 7.61 | H32: =F32*G32 -> 8.7515 | I32: LIXO
A33: SUCO DE LARANJA COM MAMAO | B33: 2.5 | E33: 0.842 | F33: =B33+C33-E33 -> 1.658 | G33: =8.84*3+4.33 -> 30.85 | H33: =F33*G33 -> 51.1493 | I33: LIXO
A34: SUCO DE LARANJA | B34: 2 | C34: =1.5+1+1.022 -> 3.522 | E34: 1.022 | F34: =B34+C34-E34 -> 4.5 | G34: 8.84 | H34: =F34*G34 -> 39.78 | I34: LIXO
A35: TOMATE ASSADO | B35: =1.888-0.66 -> 1.228 | E35: =1.434-0.66 -> 0.774 | F35: =B35+C35-E35 -> 0.454 | G35: 5.95 | H35: =F35*G35 -> 2.7013 | I35: LIXO
G36: TOTAL | H36: =SUM(H2:H35) -> 583.60008

Sheet DESCARTE
A1: CONTAGEM CAFÉ DA MANHÃ
A2: ITEM | B2: DESCARTE | C2: PREÇO KG | D2: VALOR REAL
A3: ABACAXI | B3: 0.448 | C3: 4.05 | D3: =B3*C3 -> 1.8144
A4: BATATA DOCE | B4: 0.646 | C4: 5.36 | D4: =B4*C4 -> 3.46256
A5: BOLO | B5: 0.386 | C5: 7.01 | D5: =B5*C5 -> 2.70586
A6: CALABRESA | B6: 0.672 | C6: 18.99 | D6: =B6*C6 -> 12.76128
A7: CHOCOLATE | B7: 0.522 | C7: 77.14 | D7: =B7*C7 -> 40.26708
A8: SUCO DETOX | B8: 0.5 | C8: 8.84 | D8: =B8*C8 -> 4.42
A9: IOGURTE DE MORANGO | B9: 0.08 | C9: 15.6 | D9: =B9*C9 -> 1.248
A10: LEITE INTEGRAL | B10: 4.91 | C10: 5.35 | D10: =B10*C10 -> 26.2685
A11: MAMAO | B11: 0.102 | C11: 4.33 | D11: =B11*C11 -> 0.44166
A12: MELANCIA | B12: 1.822 | C12: 3.19 | D12: =B12*C12 -> 5.81218
A13: MELÃO | B13: 0.972 | C13: 10.6 | D13: =B13*C13 -> 10.3032
A14: MILHO | B14: 0.53 | C14: 8.12 | D14: =B14*C14 -> 4.3036
A15: MINI BISNAGA C/ CREME 30G | B15: 8 | C15: =9.6/10 -> 0.96 | D15: =B15*C15 -> 7.68
A16: MINI CIABATA SIMPLES | B16: 10 | C16: =9.9/10 -> 0.99 | D16: =B16*C16 -> 9.9
A17: MINI BISNAGA C/ COCO 30G | B17: 10 | C17: =9.6/10 -> 0.96 | D17: =B17*C17 -> 9.6
A18: BAGUETE SIMPLES 60CM | B18: 0.5 | C18: 11.66 | D18: =B18*C18 -> 5.83
A19: MINI PÃO DE BATATA SIMPLES 30G | B19: 4 | C19: =9.9/10 -> 0.99 | D19: =B19*C19 -> 3.96
A20: MINI PÃO FRANCÊS 30G | B20: 27 | C20: =34/50 -> 0.68 | D20: =B20*C20 -> 18.36
A21: MINI ROSETA DE AÇÚCAR | B21: 5 | C21: =5.05/5 -> 1.01 | D21: =B21*C21 -> 5.05
A22: MINI ROSETA DE LARANJA | B22: 5 | C22: =4.8/5 -> 0.96 | D22: =B22*C22 -> 4.8
A23: MINI PÃO FRANCÊS INTEGRAL 30G | B23: 10 | C23: =8.5/10 -> 0.85 | D23: =B23*C23 -> 8.5
A24: MINI ROSETA DE COCO | B24: 2 | C24: =5.05/5 -> 1.01 | D24: =B24*C24 -> 2.02
A25: MINI PÃO MULTIGRÃO RESONDO 30G | B25: 4 | C25: =6.05/5 -> 1.21 | D25: =B25*C25 -> 4.84
A26: MINI BRIOCHE SIMPLES | B26: 5 | C26: =5.4/5 -> 1.08 | D26: =B26*C26 -> 5.4
A27: MINI PÃO DE BETERRABA 30G | B27: 4 | C27: =6.05/5 -> 1.21 | D27: =B27*C27 -> 4.84
A28: MINI PÃO DE MILHO REDONDO | B28: 3 | C28: =4.95/5 -> 0.99 | D28: =B28*C28 -> 2.97
A29: MUSSARELA | B29: 0.252 | C29: 41.9 | D29: =B29*C29 -> 10.5588
A30: MIX DE SALADAS | B30: 0.23 | C30: 56.07 | D30: =B30*C30 -> 12.8961
A31: OVO MEXIDO | B31: 1.616 | C31: 16.9 | D31: =B31*C31 -> 27.3104
A32: OVO COZIDO | B32: 10 | C32: 0.5 | D32: =B32*C32 -> 5
A33: PÃO DE QUEIJO | B33: 1.914 | C33: 16.25 | D33: =B33*C33 -> 31.1025
A34: PEITO DE PERU | B34: 0.27 | C34: 44.41 | D34: =B34*C34 -> 11.9907
A35: PRESUNTO | B35: 0.342 | C35: 28.9 | D35: =B35*C35 -> 9.8838
A36: QUEIJO MINAS | B36: 0.213 | C36: 36.65 | D36: =B36*C36 -> 7.80645
A37: QUEIJO PRATO | B37: 0.23 | C37: 41.78 | D37: =B37*C37 -> 9.6094
A38: QUICHE | B38: 0.348 | C38: 11.85 | D38: =B38*C38 -> 4.1238
A39: SALADA DE FRUTAS | B39: 0.578 | D39: =B39*C39 -> 0
A40: SALSICHA | B40: 1.476 | C40: 7.61 | D40: =B40*C40 -> 11.23236
A41: SUCO DE MELANCIA | B41: 2.5 | C41: =3.19*3 -> 9.57 | D41: =B41*C41 -> 23.925
A42: SUCO DE LARANJA COM MAMAO | B42: 0.842 | C42: =8.84*3+4.33 -> 30.85 | D42: =B42*C42 -> 25.9757
A43: SUCO DE LARANJA | B43: 1.022 | C43: 8.84 | D43: =B43*C43 -> 9.03448
A44: TOMATE ASSADO | B44: 0.774 | C44: 5.95 | D44: =B44*C44 -> 4.6053
C45: TOTAL | D45: =SUM(D3:D44) -> 412.61311

Sheet PAINEL
B2: RELATÓRIO OPERACIONAL · CAFÉ DA MANHÃ · COMPETÊNCIA MÊS 09 · VERSÃO FINAL
B3: CUSTO & DESCARTE DO CAFÉ DA MANHÃ
B6: Custo total do período | E6: CMV (custo / receita CDM) | H6: Valor total descartado | K6: Descarte sobre o custo | N6: Pessoas atendidas | Q6: Descarte por pessoa
B7: =CUSTO!H144 -> 1103.5386 | E7: =CUSTO!H144/CUSTO!E149 -> 0.2894148 | H7: =DESCARTE!D45 -> 412.61311 | K7: =DESCARTE!D45/CUSTO!H144 -> 0.37390002 | N7: =CUSTO!B146+CUSTO!B148 -> 80 | Q7: =DESCARTE!D45/(CUSTO!B146+CUSTO!B148) -> 5.1576639
B8: ="Receita de "&TEXT(CUSTO!E149,"R$ #,##0") -> Receita de R$ 3813,0 | E8: ="Custo "&TEXT(CUSTO!H144,"R$ #,##0")&" / receita "&TEXT(CUSTO!E149,"R$ #,##0") -> Custo R$ 1103,539 / receita R$ 3813,0 | H8: ="42 itens com descarte registrado" -> 42 itens com descarte registrado | K8: =TEXT(DESCARTE!D45/CUSTO!E149,"0.0%")&" da receita do período" -> 11% da receita do período | N8: =CUSTO!B146&" diárias c/ café + "&CUSTO!B148&" passantes" -> 73 diárias c/ café + 7 passantes | Q8: ="Custo/pessoa "&TEXT(CUSTO!H144/(CUSTO!B146+CUSTO!B148),"R$ #,##0.00") -> Custo/pessoa R$ 13,79423
B35: BASE DE APOIO DOS GRÁFICOS (fórmulas ligadas às abas CUSTO/DESCARTE — não altera os dados de origem)
B36: Item | C36: Categoria | D36: Qtd (kg) | E36: Preço/kg | F36: Valor (R$) | G36: % do total | H36: Item (lookup) | I36: Categoria | J36: Rank | L36: Top 10 · Item | M36: Valor (R$) | O36: Categoria | P36: Valor (R$) | R36: Origem | S36: Receita (R$)
B37: =DESCARTE!A3 -> ABACAXI | C37: =IFERROR(VLOOKUP(B37,$H$37:$I$78,2,0),"Outros") -> Frutas | D37: =DESCARTE!B3 -> 0.448 | E37: =DESCARTE!C3 -> 4.05 | F37: =DESCARTE!D3 -> 1.8144 | G37: =F37/$F$79 -> 0.0043973397 | H37: ABACAXI | I37: Frutas | J37: =RANK(F37,$F$37:$F$78)+COUNTIF($F$37:F37,F37)-1 -> 39 | L37: =INDEX($B$37:$B$78,MATCH(1,$J$37:$J$78,0)) -> CHOCOLATE | M37: =INDEX($F$37:$F$78,MATCH(1,$J$37:$J$78,0)) -> 40.26708 | O37: Padaria | P37: =SUMIF($C$37:$C$78,O37,$F$37:$F$78) -> 124.8525 | R37: Hóspedes (café incluso) | S37: =CUSTO!E146 -> 3358
B38: =DESCARTE!A4 -> BATATA DOCE | C38: =IFERROR(VLOOKUP(B38,$H$37:$I$78,2,0),"Outros") -> Guarnições | D38: =DESCARTE!B4 -> 0.646 | E38: =DESCARTE!C4 -> 5.36 | F38: =DESCARTE!D4 -> 3.46256 | G38: =F38/$F$79 -> 0.0083917838 | H38: MAMAO | I38: Frutas | J38: =RANK(F38,$F$37:$F$78)+COUNTIF($F$37:F38,F38)-1 -> 35 | L38: =INDEX($B$37:$B$78,MATCH(2,$J$37:$J$78,0)) -> PÃO DE QUEIJO | M38: =INDEX($F$37:$F$78,MATCH(2,$J$37:$J$78,0)) -> 31.1025 | O38: Proteínas | P38: =SUMIF($C$37:$C$78,O38,$F$37:$F$78) -> 82.30234 | R38: Passantes (avulso) | S38: =CUSTO!E148 -> 455
B39: =DESCARTE!A5 -> BOLO | C39: =IFERROR(VLOOKUP(B39,$H$37:$I$78,2,0),"Outros") -> Doces | D39: =DESCARTE!B5 -> 0.386 | E39: =DESCARTE!C5 -> 7.01 | F39: =DESCARTE!D5 -> 2.70586 | G39: =F39/$F$79 -> 0.0065578624 | H39: MELANCIA | I39: Frutas | J39: =RANK(F39,$F$37:$F$78)+COUNTIF($F$37:F39,F39)-1 -> 37 | L39: =INDEX($B$37:$B$78,MATCH(3,$J$37:$J$78,0)) -> OVO MEXIDO | M39: =INDEX($F$37:$F$78,MATCH(3,$J$37:$J$78,0)) -> 27.3104 | O39: Bebidas | P39: =SUMIF($C$37:$C$78,O39,$F$37:$F$78) -> 63.35518
B40: =DESCARTE!A6 -> CALABRESA | C40: =IFERROR(VLOOKUP(B40,$H$37:$I$78,2,0),"Outros") -> Proteínas | D40: =DESCARTE!B6 -> 0.672 | E40: =DESCARTE!C6 -> 18.99 | F40: =DESCARTE!D6 -> 12.76128 | G40: =F40/$F$79 -> 0.030927956 | H40: MELÃO | I40: Frutas | J40: =RANK(F40,$F$37:$F$78)+COUNTIF($F$37:F40,F40)-1 -> 9 | L40: =INDEX($B$37:$B$78,MATCH(4,$J$37:$J$78,0)) -> LEITE INTEGRAL | M40: =INDEX($F$37:$F$78,MATCH(4,$J$37:$J$78,0)) -> 26.2685 | O40: Doces | P40: =SUMIF($C$37:$C$78,O40,$F$37:$F$78) -> 42.97294
B41: =DESCARTE!A7 -> CHOCOLATE | C41: =IFERROR(VLOOKUP(B41,$H$37:$I$78,2,0),"Outros") -> Doces | D41: =DESCARTE!B7 -> 0.522 | E41: =DESCARTE!C7 -> 77.14 | F41: =DESCARTE!D7 -> 40.26708 | G41: =F41/$F$79 -> 0.097590404 | H41: SALADA DE FRUTAS | I41: Frutas | J41: =RANK(F41,$F$37:$F$78)+COUNTIF($F$37:F41,F41)-1 -> 1 | L41: =INDEX($B$37:$B$78,MATCH(5,$J$37:$J$78,0)) -> SUCO DE LARANJA COM MAMAO | M41: =INDEX($F$37:$F$78,MATCH(5,$J$37:$J$78,0)) -> 25.9757 | O41: Laticínios | P41: =SUMIF($C$37:$C$78,O41,$F$37:$F$78) -> 55.49115
B42: =DESCARTE!A8 -> SUCO DETOX | C42: =IFERROR(VLOOKUP(B42,$H$37:$I$78,2,0),"Outros") -> Bebidas | D42: =DESCARTE!B8 -> 0.5 | E42: =DESCARTE!C8 -> 8.84 | F42: =DESCARTE!D8 -> 4.42 | G42: =F42/$F$79 -> 0.010712214 | H42: BOLO | I42: Doces | J42: =RANK(F42,$F$37:$F$78)+COUNTIF($F$37:F42,F42)-1 -> 31 | L42: =INDEX($B$37:$B$78,MATCH(6,$J$37:$J$78,0)) -> SUCO DE MELANCIA | M42: =INDEX($F$37:$F$78,MATCH(6,$J$37:$J$78,0)) -> 23.925 | O42: Guarnições | P42: =SUMIF($C$37:$C$78,O42,$F$37:$F$78) -> 25.26756
B43: =DESCARTE!A9 -> IOGURTE DE MORANGO | C43: =IFERROR(VLOOKUP(B43,$H$37:$I$78,2,0),"Outros") -> Laticínios | D43: =DESCARTE!B9 -> 0.08 | E43: =DESCARTE!C9 -> 15.6 | F43: =DESCARTE!D9 -> 1.248 | G43: =F43/$F$79 -> 0.0030246252 | H43: CHOCOLATE | I43: Doces | J43: =RANK(F43,$F$37:$F$78)+COUNTIF($F$37:F43,F43)-1 -> 40 | L43: =INDEX($B$37:$B$78,MATCH(7,$J$37:$J$78,0)) -> MINI PÃO FRANCÊS 30G | M43: =INDEX($F$37:$F$78,MATCH(7,$J$37:$J$78,0)) -> 18.36 | O43: Frutas | P43: =SUMIF($C$37:$C$78,O43,$F$37:$F$78) -> 18.37144
B44: =DESCARTE!A10 -> LEITE INTEGRAL | C44: =IFERROR(VLOOKUP(B44,$H$37:$I$78,2,0),"Outros") -> Laticínios | D44: =DESCARTE!B10 -> 4.91 | E44: =DESCARTE!C10 -> 5.35 | F44: =DESCARTE!D10 -> 26.2685 | G44: =F44/$F$79 -> 0.063663755 | H44: SUCO DETOX | I44: Bebidas | J44: =RANK(F44,$F$37:$F$78)+COUNTIF($F$37:F44,F44)-1 -> 4 | L44: =INDEX($B$37:$B$78,MATCH(8,$J$37:$J$78,0)) -> MIX DE SALADAS | M44: =INDEX($F$37:$F$78,MATCH(8,$J$37:$J$78,0)) -> 12.8961 | O44: Outros | P44: =SUMIF($C$37:$C$78,O44,$F$37:$F$78) -> 0
B45: =DESCARTE!A11 -> MAMAO | C45: =IFERROR(VLOOKUP(B45,$H$37:$I$78,2,0),"Outros") -> Frutas | D45: =DESCARTE!B11 -> 0.102 | E45: =DESCARTE!C11 -> 4.33 | F45: =DESCARTE!D11 -> 0.44166 | G45: =F45/$F$79 -> 0.0010703974 | H45: SUCO DE MELANCIA | I45: Bebidas | J45: =RANK(F45,$F$37:$F$78)+COUNTIF($F$37:F45,F45)-1 -> 41 | L45: =INDEX($B$37:$B$78,MATCH(9,$J$37:$J$78,0)) -> CALABRESA | M45: =INDEX($F$37:$F$78,MATCH(9,$J$37:$J$78,0)) -> 12.76128
B46: =DESCARTE!A12 -> MELANCIA | C46: =IFERROR(VLOOKUP(B46,$H$37:$I$78,2,0),"Outros") -> Frutas | D46: =DESCARTE!B12 -> 1.822 | E46: =DESCARTE!C12 -> 3.19 | F46: =DESCARTE!D12 -> 5.81218 | G46: =F46/$F$79 -> 0.014086271 | H46: SUCO DE LARANJA COM MAMAO | I46: Bebidas | J46: =RANK(F46,$F$37:$F$78)+COUNTIF($F$37:F46,F46)-1 -> 23 | L46: =INDEX($B$37:$B$78,MATCH(10,$J$37:$J$78,0)) -> PEITO DE PERU | M46: =INDEX($F$37:$F$78,MATCH(10,$J$37:$J$78,0)) -> 11.9907
B47: =DESCARTE!A13 -> MELÃO | C47: =IFERROR(VLOOKUP(B47,$H$37:$I$78,2,0),"Outros") -> Frutas | D47: =DESCARTE!B13 -> 0.972 | E47: =DESCARTE!C13 -> 10.6 | F47: =DESCARTE!D13 -> 10.3032 | G47: =F47/$F$79 -> 0.024970607 | H47: SUCO DE LARANJA | I47: Bebidas | J47: =RANK(F47,$F$37:$F$78)+COUNTIF($F$37:F47,F47)-1 -> 13
B48: =DESCARTE!A14 -> MILHO | C48: =IFERROR(VLOOKUP(B48,$H$37:$I$78,2,0),"Outros") -> Guarnições | D48: =DESCARTE!B14 -> 0.53 | E48: =DESCARTE!C14 -> 8.12 | F48: =DESCARTE!D14 -> 4.3036 | G48: =F48/$F$79 -> 0.01043011 | H48: IOGURTE DE MORANGO | I48: Laticínios | J48: =RANK(F48,$F$37:$F$78)+COUNTIF($F$37:F48,F48)-1 -> 32
B49: =DESCARTE!A15 -> MINI BISNAGA C/ CREME 30G | C49: =IFERROR(VLOOKUP(B49,$H$37:$I$78,2,0),"Outros") -> Padaria | D49: =DESCARTE!B15 -> 8 | E49: =DESCARTE!C15 -> 0.96 | F49: =DESCARTE!D15 -> 7.68 | G49: =F49/$F$79 -> 0.018613078 | H49: LEITE INTEGRAL | I49: Laticínios | J49: =RANK(F49,$F$37:$F$78)+COUNTIF($F$37:F49,F49)-1 -> 21
B50: =DESCARTE!A16 -> MINI CIABATA SIMPLES | C50: =IFERROR(VLOOKUP(B50,$H$37:$I$78,2,0),"Outros") -> Padaria | D50: =DESCARTE!B16 -> 10 | E50: =DESCARTE!C16 -> 0.99 | F50: =DESCARTE!D16 -> 9.9 | G50: =F50/$F$79 -> 0.023993421 | H50: MUSSARELA | I50: Laticínios | J50: =RANK(F50,$F$37:$F$78)+COUNTIF($F$37:F50,F50)-1 -> 14
B51: =DESCARTE!A17 -> MINI BISNAGA C/ COCO 30G | C51: =IFERROR(VLOOKUP(B51,$H$37:$I$78,2,0),"Outros") -> Padaria | D51: =DESCARTE!B17 -> 10 | E51: =DESCARTE!C17 -> 0.96 | F51: =DESCARTE!D17 -> 9.6 | G51: =F51/$F$79 -> 0.023266347 | H51: QUEIJO MINAS | I51: Laticínios | J51: =RANK(F51,$F$37:$F$78)+COUNTIF($F$37:F51,F51)-1 -> 17
B52: =DESCARTE!A18 -> BAGUETE SIMPLES 60CM | C52: =IFERROR(VLOOKUP(B52,$H$37:$I$78,2,0),"Outros") -> Padaria | D52: =DESCARTE!B18 -> 0.5 | E52: =DESCARTE!C18 -> 11.66 | F52: =DESCARTE!D18 -> 5.83 | G52: =F52/$F$79 -> 0.014129459 | H52: QUEIJO PRATO | I52: Laticínios | J52: =RANK(F52,$F$37:$F$78)+COUNTIF($F$37:F52,F52)-1 -> 22
B53: =DESCARTE!A19 -> MINI PÃO DE BATATA SIMPLES 30G | C53: =IFERROR(VLOOKUP(B53,$H$37:$I$78,2,0),"Outros") -> Padaria | D53: =DESCARTE!B19 -> 4 | E53: =DESCARTE!C19 -> 0.99 | F53: =DESCARTE!D19 -> 3.96 | G53: =F53/$F$79 -> 0.0095973683 | H53: CALABRESA | I53: Proteínas | J53: =RANK(F53,$F$37:$F$78)+COUNTIF($F$37:F53,F53)-1 -> 34
B54: =DESCARTE!A20 -> MINI PÃO FRANCÊS 30G | C54: =IFERROR(VLOOKUP(B54,$H$37:$I$78,2,0),"Outros") -> Padaria | D54: =DESCARTE!B20 -> 27 | E54: =DESCARTE!C20 -> 0.68 | F54: =DESCARTE!D20 -> 18.36 | G54: =F54/$F$79 -> 0.04449689 | H54: OVO MEXIDO | I54: Proteínas | J54: =RANK(F54,$F$37:$F$78)+COUNTIF($F$37:F54,F54)-1 -> 7
B55: =DESCARTE!A21 -> MINI ROSETA DE AÇÚCAR | C55: =IFERROR(VLOOKUP(B55,$H$37:$I$78,2,0),"Outros") -> Padaria | D55: =DESCARTE!B21 -> 5 | E55: =DESCARTE!C21 -> 1.01 | F55: =DESCARTE!D21 -> 5.05 | G55: =F55/$F$79 -> 0.012239068 | H55: OVO COZIDO | I55: Proteínas | J55: =RANK(F55,$F$37:$F$78)+COUNTIF($F$37:F55,F55)-1 -> 25
B56: =DESCARTE!A22 -> MINI ROSETA DE LARANJA | C56: =IFERROR(VLOOKUP(B56,$H$37:$I$78,2,0),"Outros") -> Padaria | D56: =DESCARTE!B22 -> 5 | E56: =DESCARTE!C22 -> 0.96 | F56: =DESCARTE!D22 -> 4.8 | G56: =F56/$F$79 -> 0.011633174 | H56: PEITO DE PERU | I56: Proteínas | J56: =RANK(F56,$F$37:$F$78)+COUNTIF($F$37:F56,F56)-1 -> 29
B57: =DESCARTE!A23 -> MINI PÃO FRANCÊS INTEGRAL 30G | C57: =IFERROR(VLOOKUP(B57,$H$37:$I$78,2,0),"Outros") -> Padaria | D57: =DESCARTE!B23 -> 10 | E57: =DESCARTE!C23 -> 0.85 | F57: =DESCARTE!D23 -> 8.5 | G57: =F57/$F$79 -> 0.020600412 | H57: PRESUNTO | I57: Proteínas | J57: =RANK(F57,$F$37:$F$78)+COUNTIF($F$37:F57,F57)-1 -> 19
B58: =DESCARTE!A24 -> MINI ROSETA DE COCO | C58: =IFERROR(VLOOKUP(B58,$H$37:$I$78,2,0),"Outros") -> Padaria | D58: =DESCARTE!B24 -> 2 | E58: =DESCARTE!C24 -> 1.01 | F58: =DESCARTE!D24 -> 2.02 | G58: =F58/$F$79 -> 0.0048956273 | H58: SALSICHA | I58: Proteínas | J58: =RANK(F58,$F$37:$F$78)+COUNTIF($F$37:F58,F58)-1 -> 38
... B78: =DESCARTE!A44 -> TOMATE ASSADO | C78: =IFERROR(VLOOKUP(B78,$H$37:$I$78,2,0),"Outros") -> Guarnições | D78: =DESCARTE!B44 -> 0.774 | E78: =DESCARTE!C44 -> 5.95 | F78: =DESCARTE!D44 -> 4.6053 | G78: =F78/$F$79 -> 0.011161303 | H78: PÃO DE QUEIJO | I78: Padaria | J78: =RANK(F78,$F$37:$F$78)+COUNTIF($F$37:F78,F78)-1 -> 30
B79: TOTAL | F79: =SUM(F37:F78) -> 412.61311

Sheet DASHBOARD

Sheet BOLO BASE
A1: BOLO BASE | C1: Número de porções: | G1: 1 | H1: Código Receita Nº
A3: Cód. SAP | B3: Ingrediente | C3: Peso | E3: Und | G3: Custo Bruto | H3: Rendimento | I3: Preço Líquido | J3: Custo Total
B4: OVOS | C4: 0.1 | G4: =CUSTO!G111 -> 41.9 | H4: 1 | I4: =G4/H4 -> 41.9 | J4: =C4*I4 -> 4.19
B5: AÇUCAR | C5: 0.2 | G5: 4.37 | H5: 1 | I5: =G5/H5 -> 4.37 | J5: =C5*I5 -> 0.874
B6: OLEO | C6: 0.1 | G6: 8.78 | H6: 1 | I6: =G6/H6 -> 8.78 | J6: =C6*I6 -> 0.878
B7: LEITE | C7: 0.2 | G7: 4.75 | H7: 1 | I7: =G7/H7 -> 4.75 | J7: =C7*I7 -> 0.95
B8: ESSENCIA DE BAUNILHA | C8: 0.01 | G8: 11.76 | H8: 1 | I8: =G8/H8 -> 11.76 | J8: =C8*I8 -> 0.1176
J9: =SUM(J4:J8) -> 7.0096
B10: Custo Líquido | C10: Análise de preço de venda estimado
A11: Análise de Custo | C11: Custos | E11: % Margem | J11: Preço CUSTO
C12: R$ | D12: % | E12: R$ | F12: %
C13: =J9 -> 7.0096 | D13: 0.3 | J13: =J9 -> 7.0096

Sheet COBERTURA
A1: COBERTURA DE CHOCOLATE | C1: Número de porções: | G1: 1 | H1: Código Receita Nº
A3: Cód. SAP | B3: Ingrediente | C3: Peso | E3: Und | G3: Custo Bruto | H3: Rendimento | I3: Preço Líquido | J3: Custo Total
B4: CHOCOLATE | C4: 0.05 | G4: 46.2 | H4: 1 | I4: =G4/H4 -> 46.2 | J4: =C4*I4 -> 2.31
B5: CREME DE LEITE | C5: 0.05 | G5: 4.56 | H5: 1 | I5: =G5/H5 -> 4.56 | J5: =C5*I5 -> 0.228
C6: R$ | D6: % | E6: R$ | F6: % | J6: =SUM(J4:J5) -> 2.538
C7: =J6 -> 2.538 | D7: 0.3

Sheet QUICHE
A1: QUICHE | C1: Número de porções: | G1: 1 | H1: Código Receita Nº
A3: Cód. SAP | B3: Ingrediente | C3: Peso | E3: Und | G3: Custo Bruto | H3: Rendimento | I3: Preço Líquido | J3: Custo Total
B4: FARINHA DE TRIGO | C4: 0.5 | G4: 6.85 | H4: 1 | I4: =G4/H4 -> 6.85 | J4: =C4*I4 -> 3.425
B5: MARGARINA | C5: 0.3 | G5: 14.94 | H5: 1 | I5: =G5/H5 -> 14.94 | J5: =C5*I5 -> 4.482
B6: OVO | C6: 0.25 | G6: 11.2 | H6: 1 | I6: =G6/H6 -> 11.2 | J6: =C6*I6 -> 2.8
B7: AGUA GELADA | C7: 0.03 | G7: 7.23 | H7: 1 | I7: =G7/H7 -> 7.23 | J7: =C7*I7 -> 0.2169
B8: CREME DE LEITE | C8: 0.2 | G8: 4.56 | H8: 1 | I8: =G8/H8 -> 4.56 | J8: =C8*I8 -> 0.912
B9: SAL | C9: 0.01 | G9: 0.99 | H9: 1 | I9: =G9/H9 -> 0.99 | J9: =C9*I9 -> 0.0099
J10: =SUM(J4:J9) -> 11.8458
B11: Custo Líquido | C11: Análise de preço de venda estimado
A12: Análise de Custo | C12: Custos | E12: % Margem | J12: PREÇO CUSTO
C13: R$ | D13: % | E13: R$ | F13: %
C14: =J10 -> 11.8458 | D14: 0.3 | J14: =J10 -> 11.8458

Sheet PANQUECA WAFFLE
A1: PANQUECA | C1: Número de porções: | G1: 50 | H1: Código Receita Nº
A3: Cód. SAP | B3: Ingrediente | C3: Peso | E3: Und | G3: Custo Bruto | H3: Rendimento | I3: Preço Líquido | J3: Custo Total
B4: OVOS | C4: 0.2 | G4: 11.2 | H4: 1 | I4: =G4/H4 -> 11.2 | J4: =C4*I4 -> 2.24
B5: OLEO | C5: 0.1 | G5: 8.78 | H5: 1 | I5: =G5/H5 -> 8.78 | J5: =C5*I5 -> 0.878
B6: MARGARINA | C6: 0.02 | G6: 14.94 | H6: 1 | I6: =G6/H6 -> 14.94 | J6: =C6*I6 -> 0.2988
B7: LEITE | C7: 1 | G7: 4.75 | H7: 1 | I7: =G7/H7 -> 4.75 | J7: =C7*I7 -> 4.75
B8: TRIGO | C8: 0.9 | G8: 6.85 | H8: 1 | I8: =G8/H8 -> 6.85 | J8: =C8*I8 -> 6.165
B9: ESSENCIA BAUNILHA | C9: 0.01 | G9: 11.76 | H9: 1 | I9: =G9/H9 -> 11.76 | J9: =C9*I9 -> 0.1176
B10: FERMENTO EM PÓ | C10: 0.01 | G10: 33.45 | H10: 1 | I10: =G10/H10 -> 33.45 | J10: =C10*I10 -> 0.3345
J11: =SUM(J4:J10) -> 14.7839
B12: Custo Líquido | C12: Análise de preço de venda estimado
A13: Análise de Custo | C13: Custos | E13: % Margem | J13: Preço CUSTO UNITARIO
C14: R$ | D14: % | E14: R$ | F14: %
C15: =J11 -> 14.7839 | D15: 0.3 | J15: =(C15/D15)/G1 -> 0.98559333

Sheet SUCO VERDE
A1: SUCO VERDE | C1: Número de porções: | G1: 1 | H1: Código Receita Nº
A3: Cód. SAP | B3: Ingrediente | C3: Peso | E3: Und | G3: Custo Bruto | H3: Rendimento | I3: Preço Líquido | J3: Custo Total
B4: COUVE | C4: 0.01 | G4: 7.04 | H4: 1 | I4: =G4/H4 -> 7.04 | J4: =C4*I4 -> 0.0704
B5: GENGIBRE | C5: 0.05 | G5: 7.24 | H5: 1 | I5: =G5/H5 -> 7.24 | J5: =C5*I5 -> 0.362
B6: ABACAXI | C6: 0.15 | G6: 4.83 | H6: 1 | I6: =G6/H6 -> 4.83 | J6: =C6*I6 -> 0.7245
B7: HORTELÃ | C7: 0.01 | G7: 11.6 | H7: 1 | I7: =G7/H7 -> 11.6 | J7: =C7*I7 -> 0.116
B8: MAÇA VERDE | C8: 0.1 | G8: 14.48 | H8: 1 | I8: =G8/H8 -> 14.48 | J8: =C8*I8 -> 1.448
J9: =SUM(J4:J8) -> 2.7209
B10: Custo Líquido | C10: Análise de preço de venda estimado
A11: Análise de Custo | C11: Custos | E11: % Margem | J11: PREÇO CUSTO
C12: R$ | D12: % | E12: R$ | F12: %
C13: =J9 -> 2.7209 | D13: 0.3 | J13: =J9 -> 2.7209
